marshalparser/__init__.py
marshalparser/__main__.py
marshalparser/bits.py
marshalparser/magic.py
marshalparser/marshalparser.py
marshalparser/object_types.py
marshalparser-0.5.0.dist-info/licenses/LICENSE
marshalparser-0.5.0.dist-info/METADATA
marshalparser-0.5.0.dist-info/WHEEL
marshalparser-0.5.0.dist-info/entry_points.txt
marshalparser-0.5.0.dist-info/top_level.txt
marshalparser-0.5.0.dist-info/RECORD
