Metadata-Version: 2.4
Name: marshalparser
Version: 0.5.0
Summary: Parser for byte-cache .pyc files
Home-page: https://github.com/fedora-python/marshalparser/
Author: Lumír Balhar
Author-email: frenzy.madness@gmail.com
License: MIT
Classifier: Development Status :: 5 - Production/Stable
Classifier: Intended Audience :: Developers
Classifier: Programming Language :: Python :: 3
Classifier: Programming Language :: Python :: 3.6
Classifier: Programming Language :: Python :: 3.7
Classifier: Programming Language :: Python :: 3.8
Classifier: Programming Language :: Python :: 3.9
Classifier: Programming Language :: Python :: 3.10
Classifier: Programming Language :: Python :: 3.11
Classifier: Programming Language :: Python :: 3.12
Classifier: Programming Language :: Python :: 3.13
Classifier: Programming Language :: Python :: 3.14
Classifier: Programming Language :: Python :: 3.15
Classifier: Programming Language :: Python :: Implementation :: CPython
Classifier: License :: OSI Approved :: MIT License
Classifier: Operating System :: POSIX :: Linux
Classifier: Topic :: Software Development :: Compilers
License-File: LICENSE
Requires-Dist: dataclasses; python_version < "3.7"
Provides-Extra: test
Requires-Dist: pytest>=6; extra == "test"
Dynamic: license-file
